barrel_shifter.v
module mux2 (input wire i0, i1, j, output wire o);
  assign o = (j==0)?i0:i1;
endmodule

module barrel_shift_16bit (in, ctrl, out);
  input  [15:0] in; 
  input [3:0] ctrl;  
  output [15:0] out;   
  wire [15:0] x,y,z;

mux2 mux_15(in[15],1'b0,ctrl[3],x[15]);
mux2 mux_14(in[14],1'b0,ctrl[3],x[14]);
mux2 mux_13(in[13],1'b0,ctrl[3],x[13]);
mux2 mux_12(in[12],1'b0,ctrl[3],x[12]);
mux2 mux_11(in[11],1'b0,ctrl[3],x[11]);
mux2 mux_10(in[10],1'b0,ctrl[3],x[10]);
mux2 mux_9(in[9],1'b0,ctrl[3],x[9]);
mux2 mux_8(in[8],1'b0,ctrl[3],x[8]);
mux2 mux_7(in[7],in[15],ctrl[3],x[7]);
mux2 mux_6(in[6],in[14],ctrl[3],x[6]);
mux2 mux_5(in[5],in[13],ctrl[3],x[5]);
mux2 mux_4(in[4],in[12],ctrl[3],x[4]);
mux2 mux_3(in[3],in[11],ctrl[3],x[3]);
mux2 mux_2(in[2],in[10],ctrl[3],x[2]);
mux2 mux_1(in[1],in[9],ctrl[3],x[1]);
mux2 mux_0(in[0],in[8],ctrl[3],x[0]);


mux2 mux_31(x[15],1'b0,ctrl[2],y[15]);
mux2 mux_30(x[14],1'b0,ctrl[2],y[14]);
mux2 mux_29(x[13],1'b0,ctrl[2],y[13]);
mux2 mux_28(x[12],1'b0,ctrl[2],y[12]);
mux2 mux_27(x[11],x[15],ctrl[2],y[11]);
mux2 mux_26(x[10],x[14],ctrl[2],y[10]);
mux2 mux_25(x[9],x[13],ctrl[2],y[9]);
mux2 mux_24(x[8],x[12],ctrl[2],y[8]);
mux2 mux_23(x[7],x[11],ctrl[2],y[7]);
mux2 mux_22(x[6],x[10],ctrl[2],y[6]);
mux2 mux_21(x[5],x[9],ctrl[2],y[5]);
mux2 mux_20(x[4],x[8],ctrl[2],y[4]);
mux2 mux_19(x[3],x[7],ctrl[2],y[3]);
mux2 mux_18(x[2],x[6],ctrl[2],y[2]);
mux2 mux_17(x[1],x[5],ctrl[2],y[1]);
mux2 mux_16(x[0],x[4],ctrl[2],y[0]);


mux2 mux_47(y[15],1'b0,ctrl[1],z[15]);
mux2 mux_46(y[14],1'b0,ctrl[1],z[14]);
mux2 mux_45(y[13],y[15],ctrl[1],z[13]);
mux2 mux_44(y[12],y[14],ctrl[1],z[12]);
mux2 mux_43(y[11],y[13],ctrl[1],z[11]);
mux2 mux_42(y[10],y[12],ctrl[1],z[10]);
mux2 mux_41(y[9],y[11],ctrl[1],z[9]);
mux2 mux_40(y[8],y[10],ctrl[1],z[8]);
mux2 mux_39(y[7],y[9],ctrl[1],z[7]);
mux2 mux_38(y[6],y[8],ctrl[1],z[6]);
mux2 mux_37(y[5],y[7],ctrl[1],z[5]);
mux2 mux_36(y[4],y[6],ctrl[1],z[4]);
mux2 mux_35(y[3],y[5],ctrl[1],z[3]);
mux2 mux_34(y[2],y[4],ctrl[1],z[2]);
mux2 mux_33(y[1],y[3],ctrl[1],z[1]);
mux2 mux_32(y[0],y[2],ctrl[1],z[0]);


mux2 mux_63(z[15],1'b0,ctrl[0],out[15]);
mux2 mux_62(z[14],z[15],ctrl[0],out[14]);
mux2 mux_61(z[13],z[14],ctrl[0],out[13]);
mux2 mux_60(z[12],z[13],ctrl[0],out[12]);
mux2 mux_59(z[11],z[12],ctrl[0],out[11]);
mux2 mux_58(z[10],z[11],ctrl[0],out[10]);
mux2 mux_57(z[9],z[10],ctrl[0],out[9]);
mux2 mux_56(z[8],z[9],ctrl[0],out[8]);
mux2 mux_55(z[7],z[8],ctrl[0],out[7]);
mux2 mux_54(z[6],z[7],ctrl[0],out[6]);
mux2 mux_53(z[5],z[6],ctrl[0],out[5]);
mux2 mux_52(z[4],z[5],ctrl[0],out[4]);
mux2 mux_51(z[3],z[4],ctrl[0],out[3]);
mux2 mux_50(z[2],z[3],ctrl[0],out[2]);
mux2 mux_49(z[1],z[2],ctrl[0],out[1]);
mux2 mux_48(z[0],z[1],ctrl[0],out[0]);
endmodule

tb_barrel_shifter.v
`timescale 100 ns / 100 ps
module tb_barrel_shift_16bit;
  reg [15:0] in;
  reg [3:0] ctrl;
  wire [15:0] out; 
  initial begin $dumpfile("tb_barrel_shifter.vcd"); 
 $dumpvars(0,tb_barrel_shift_16bit); 
 end
barrel_shift_16bit bs(.in(in), .ctrl(ctrl), .out(out));
  
initial 
 begin    
         in=16'd16385; ctrl=4'd0; 
        #5 in=16'd16385; ctrl=4'd1; 
        #5 in=16'd16385; ctrl=4'd2; 
        #5 in=16'd16385; ctrl=4'd3; 
        #5 in=16'd16385; ctrl=4'd4; 
        #5 in=16'd16385; ctrl=4'd5; 
        #5 in=16'd16385; ctrl=4'd6; 
        #5 in=16'd16385; ctrl=4'd7; 
        #5 in=16'd16385; ctrl=4'd8; 
        #5 in=16'd16385; ctrl=4'd9; 
        #5 in=16'd16385; ctrl=4'd10; 
        #5 in=16'd16385; ctrl=4'd11; 
        #5 in=16'd16385; ctrl=4'd12; 
        #5 in=16'd16385; ctrl=4'd13; 
        #5 in=16'd16385; ctrl=4'd14; 
        #5 in=16'd16385; ctrl=4'd15; 
  end
    initial begin
      $monitor("Input=%d, Control=%d, Output=%d",in,ctrl,out);    
    end
endmodule

tb_project.vcd
$date
	Wed Nov 16 11:39:36 2022
$end
$version
	Icarus Verilog
$end
$timescale
	100ps
$end
$scope module tb_barrel_shift_16bit $end
$var wire 16 ! out [15:0] $end
$var reg 4 " ctrl [3:0] $end
$var reg 16 # in [15:0] $end
$scope module bs $end
$var wire 4 $ ctrl [3:0] $end
$var wire 16 % in [15:0] $end
$var wire 16 & z [15:0] $end
$var wire 16 ' y [15:0] $end
$var wire 16 ( x [15:0] $end
$var wire 16 ) out [15:0] $end
$scope module mux_0 $end
$var wire 1 * i0 $end
$var wire 1 + i1 $end
$var wire 1 , j $end
$var wire 1 - o $end
$upscope $end
$scope module mux_1 $end
$var wire 1 . i0 $end
$var wire 1 / i1 $end
$var wire 1 0 j $end
$var wire 1 1 o $end
$upscope $end
$scope module mux_10 $end
$var wire 1 2 i0 $end
$var wire 1 3 i1 $end
$var wire 1 4 j $end
$var wire 1 5 o $end
$upscope $end
$scope module mux_11 $end
$var wire 1 6 i0 $end
$var wire 1 7 i1 $end
$var wire 1 8 j $end
$var wire 1 9 o $end
$upscope $end
$scope module mux_12 $end
$var wire 1 : i0 $end
$var wire 1 ; i1 $end
$var wire 1 < j $end
$var wire 1 = o $end
$upscope $end
$scope module mux_13 $end
$var wire 1 > i0 $end
$var wire 1 ? i1 $end
$var wire 1 @ j $end
$var wire 1 A o $end
$upscope $end
$scope module mux_14 $end
$var wire 1 B i0 $end
$var wire 1 C i1 $end
$var wire 1 D j $end
$var wire 1 E o $end
$upscope $end
$scope module mux_15 $end
$var wire 1 F i0 $end
$var wire 1 G i1 $end
$var wire 1 H j $end
$var wire 1 I o $end
$upscope $end
$scope module mux_16 $end
$var wire 1 J i0 $end
$var wire 1 K i1 $end
$var wire 1 L j $end
$var wire 1 M o $end
$upscope $end
$scope module mux_17 $end
$var wire 1 N i0 $end
$var wire 1 O i1 $end
$var wire 1 P j $end
$var wire 1 Q o $end
$upscope $end
$scope module mux_18 $end
$var wire 1 R i0 $end
$var wire 1 S i1 $end
$var wire 1 T j $end
$var wire 1 U o $end
$upscope $end
$scope module mux_19 $end
$var wire 1 V i0 $end
$var wire 1 W i1 $end
$var wire 1 X j $end
$var wire 1 Y o $end
$upscope $end
$scope module mux_2 $end
$var wire 1 Z i0 $end
$var wire 1 [ i1 $end
$var wire 1 \ j $end
$var wire 1 ] o $end
$upscope $end
$scope module mux_20 $end
$var wire 1 ^ i0 $end
$var wire 1 _ i1 $end
$var wire 1 ` j $end
$var wire 1 a o $end
$upscope $end
$scope module mux_21 $end
$var wire 1 b i0 $end
$var wire 1 c i1 $end
$var wire 1 d j $end
$var wire 1 e o $end
$upscope $end
$scope module mux_22 $end
$var wire 1 f i0 $end
$var wire 1 g i1 $end
$var wire 1 h j $end
$var wire 1 i o $end
$upscope $end
$scope module mux_23 $end
$var wire 1 j i0 $end
$var wire 1 k i1 $end
$var wire 1 l j $end
$var wire 1 m o $end
$upscope $end
$scope module mux_24 $end
$var wire 1 n i0 $end
$var wire 1 o i1 $end
$var wire 1 p j $end
$var wire 1 q o $end
$upscope $end
$scope module mux_25 $end
$var wire 1 r i0 $end
$var wire 1 s i1 $end
$var wire 1 t j $end
$var wire 1 u o $end
$upscope $end
$scope module mux_26 $end
$var wire 1 v i0 $end
$var wire 1 w i1 $end
$var wire 1 x j $end
$var wire 1 y o $end
$upscope $end
$scope module mux_27 $end
$var wire 1 z i0 $end
$var wire 1 { i1 $end
$var wire 1 | j $end
$var wire 1 } o $end
$upscope $end
$scope module mux_28 $end
$var wire 1 ~ i0 $end
$var wire 1 !" i1 $end
$var wire 1 "" j $end
$var wire 1 #" o $end
$upscope $end
$scope module mux_29 $end
$var wire 1 $" i0 $end
$var wire 1 %" i1 $end
$var wire 1 &" j $end
$var wire 1 '" o $end
$upscope $end
$scope module mux_3 $end
$var wire 1 (" i0 $end
$var wire 1 )" i1 $end
$var wire 1 *" j $end
$var wire 1 +" o $end
$upscope $end
$scope module mux_30 $end
$var wire 1 ," i0 $end
$var wire 1 -" i1 $end
$var wire 1 ." j $end
$var wire 1 /" o $end
$upscope $end
$scope module mux_31 $end
$var wire 1 0" i0 $end
$var wire 1 1" i1 $end
$var wire 1 2" j $end
$var wire 1 3" o $end
$upscope $end
$scope module mux_32 $end
$var wire 1 4" i0 $end
$var wire 1 5" i1 $end
$var wire 1 6" j $end
$var wire 1 7" o $end
$upscope $end
$scope module mux_33 $end
$var wire 1 8" i0 $end
$var wire 1 9" i1 $end
$var wire 1 :" j $end
$var wire 1 ;" o $end
$upscope $end
$scope module mux_34 $end
$var wire 1 <" i0 $end
$var wire 1 =" i1 $end
$var wire 1 >" j $end
$var wire 1 ?" o $end
$upscope $end
$scope module mux_35 $end
$var wire 1 @" i0 $end
$var wire 1 A" i1 $end
$var wire 1 B" j $end
$var wire 1 C" o $end
$upscope $end
$scope module mux_36 $end
$var wire 1 D" i0 $end
$var wire 1 E" i1 $end
$var wire 1 F" j $end
$var wire 1 G" o $end
$upscope $end
$scope module mux_37 $end
$var wire 1 H" i0 $end
$var wire 1 I" i1 $end
$var wire 1 J" j $end
$var wire 1 K" o $end
$upscope $end
$scope module mux_38 $end
$var wire 1 L" i0 $end
$var wire 1 M" i1 $end
$var wire 1 N" j $end
$var wire 1 O" o $end
$upscope $end
$scope module mux_39 $end
$var wire 1 P" i0 $end
$var wire 1 Q" i1 $end
$var wire 1 R" j $end
$var wire 1 S" o $end
$upscope $end
$scope module mux_4 $end
$var wire 1 T" i0 $end
$var wire 1 U" i1 $end
$var wire 1 V" j $end
$var wire 1 W" o $end
$upscope $end
$scope module mux_40 $end
$var wire 1 X" i0 $end
$var wire 1 Y" i1 $end
$var wire 1 Z" j $end
$var wire 1 [" o $end
$upscope $end
$scope module mux_41 $end
$var wire 1 \" i0 $end
$var wire 1 ]" i1 $end
$var wire 1 ^" j $end
$var wire 1 _" o $end
$upscope $end
$scope module mux_42 $end
$var wire 1 `" i0 $end
$var wire 1 a" i1 $end
$var wire 1 b" j $end
$var wire 1 c" o $end
$upscope $end
$scope module mux_43 $end
$var wire 1 d" i0 $end
$var wire 1 e" i1 $end
$var wire 1 f" j $end
$var wire 1 g" o $end
$upscope $end
$scope module mux_44 $end
$var wire 1 h" i0 $end
$var wire 1 i" i1 $end
$var wire 1 j" j $end
$var wire 1 k" o $end
$upscope $end
$scope module mux_45 $end
$var wire 1 l" i0 $end
$var wire 1 m" i1 $end
$var wire 1 n" j $end
$var wire 1 o" o $end
$upscope $end
$scope module mux_46 $end
$var wire 1 p" i0 $end
$var wire 1 q" i1 $end
$var wire 1 r" j $end
$var wire 1 s" o $end
$upscope $end
$scope module mux_47 $end
$var wire 1 t" i0 $end
$var wire 1 u" i1 $end
$var wire 1 v" j $end
$var wire 1 w" o $end
$upscope $end
$scope module mux_48 $end
$var wire 1 x" i0 $end
$var wire 1 y" i1 $end
$var wire 1 z" j $end
$var wire 1 {" o $end
$upscope $end
$scope module mux_49 $end
$var wire 1 |" i0 $end
$var wire 1 }" i1 $end
$var wire 1 ~" j $end
$var wire 1 !# o $end
$upscope $end
$scope module mux_5 $end
$var wire 1 "# i0 $end
$var wire 1 ## i1 $end
$var wire 1 $# j $end
$var wire 1 %# o $end
$upscope $end
$scope module mux_50 $end
$var wire 1 &# i0 $end
$var wire 1 '# i1 $end
$var wire 1 (# j $end
$var wire 1 )# o $end
$upscope $end
$scope module mux_51 $end
$var wire 1 *# i0 $end
$var wire 1 +# i1 $end
$var wire 1 ,# j $end
$var wire 1 -# o $end
$upscope $end
$scope module mux_52 $end
$var wire 1 .# i0 $end
$var wire 1 /# i1 $end
$var wire 1 0# j $end
$var wire 1 1# o $end
$upscope $end
$scope module mux_53 $end
$var wire 1 2# i0 $end
$var wire 1 3# i1 $end
$var wire 1 4# j $end
$var wire 1 5# o $end
$upscope $end
$scope module mux_54 $end
$var wire 1 6# i0 $end
$var wire 1 7# i1 $end
$var wire 1 8# j $end
$var wire 1 9# o $end
$upscope $end
$scope module mux_55 $end
$var wire 1 :# i0 $end
$var wire 1 ;# i1 $end
$var wire 1 <# j $end
$var wire 1 =# o $end
$upscope $end
$scope module mux_56 $end
$var wire 1 ># i0 $end
$var wire 1 ?# i1 $end
$var wire 1 @# j $end
$var wire 1 A# o $end
$upscope $end
$scope module mux_57 $end
$var wire 1 B# i0 $end
$var wire 1 C# i1 $end
$var wire 1 D# j $end
$var wire 1 E# o $end
$upscope $end
$scope module mux_58 $end
$var wire 1 F# i0 $end
$var wire 1 G# i1 $end
$var wire 1 H# j $end
$var wire 1 I# o $end
$upscope $end
$scope module mux_59 $end
$var wire 1 J# i0 $end
$var wire 1 K# i1 $end
$var wire 1 L# j $end
$var wire 1 M# o $end
$upscope $end
$scope module mux_6 $end
$var wire 1 N# i0 $end
$var wire 1 O# i1 $end
$var wire 1 P# j $end
$var wire 1 Q# o $end
$upscope $end
$scope module mux_60 $end
$var wire 1 R# i0 $end
$var wire 1 S# i1 $end
$var wire 1 T# j $end
$var wire 1 U# o $end
$upscope $end
$scope module mux_61 $end
$var wire 1 V# i0 $end
$var wire 1 W# i1 $end
$var wire 1 X# j $end
$var wire 1 Y# o $end
$upscope $end
$scope module mux_62 $end
$var wire 1 Z# i0 $end
$var wire 1 [# i1 $end
$var wire 1 \# j $end
$var wire 1 ]# o $end
$upscope $end
$scope module mux_63 $end
$var wire 1 ^# i0 $end
$var wire 1 _# i1 $end
$var wire 1 `# j $end
$var wire 1 a# o $end
$upscope $end
$scope module mux_7 $end
$var wire 1 b# i0 $end
$var wire 1 c# i1 $end
$var wire 1 d# j $end
$var wire 1 e# o $end
$upscope $end
$scope module mux_8 $end
$var wire 1 f# i0 $end
$var wire 1 g# i1 $end
$var wire 1 h# j $end
$var wire 1 i# o $end
$upscope $end
$scope module mux_9 $end
$var wire 1 j# i0 $end
$var wire 1 k# i1 $end
$var wire 1 l# j $end
$var wire 1 m# o $end
$upscope $end
$upscope $end
$upscope $end
$enddefinitions $end
#0
$dumpvars
0m#
0l#
0k#
0j#
0i#
0h#
0g#
0f#
0e#
0d#
0c#
0b#
0a#
0`#
0_#
0^#
1]#
0\#
0[#
1Z#
0Y#
0X#
1W#
0V#
0U#
0T#
0S#
0R#
0Q#
0P#
1O#
0N#
0M#
0L#
0K#
0J#
0I#
0H#
0G#
0F#
0E#
0D#
0C#
0B#
0A#
0@#
0?#
0>#
0=#
0<#
0;#
0:#
09#
08#
07#
06#
05#
04#
03#
02#
01#
00#
0/#
0.#
0-#
0,#
0+#
0*#
0)#
0(#
0'#
0&#
0%#
0$#
0##
0"#
0!#
0~"
0}"
0|"
1{"
0z"
0y"
1x"
0w"
0v"
0u"
0t"
1s"
0r"
0q"
1p"
0o"
0n"
0m"
0l"
0k"
0j"
1i"
0h"
0g"
0f"
0e"
0d"
0c"
0b"
0a"
0`"
0_"
0^"
0]"
0\"
0["
0Z"
0Y"
0X"
0W"
0V"
0U"
0T"
0S"
0R"
0Q"
0P"
0O"
0N"
0M"
0L"
0K"
0J"
0I"
0H"
0G"
0F"
0E"
0D"
0C"
0B"
0A"
0@"
0?"
0>"
0="
0<"
0;"
0:"
09"
08"
17"
06"
05"
14"
03"
02"
01"
00"
1/"
0."
0-"
1,"
0+"
0*"
0)"
0("
0'"
0&"
0%"
0$"
0#"
0""
0!"
0~
0}
0|
0{
0z
0y
0x
1w
0v
0u
0t
0s
0r
0q
0p
0o
0n
0m
0l
0k
0j
0i
0h
0g
0f
0e
0d
0c
0b
0a
0`
0_
0^
0]
0\
0[
0Z
0Y
0X
0W
0V
0U
0T
0S
0R
0Q
0P
0O
0N
1M
0L
0K
1J
0I
0H
0G
0F
1E
0D
0C
1B
0A
0@
0?
0>
0=
0<
0;
0:
09
08
07
06
05
04
03
02
01
00
0/
0.
1-
0,
0+
1*
b100000000000001 )
b100000000000001 (
b100000000000001 '
b100000000000001 &
b100000000000001 %
b0 $
b100000000000001 #
b0 "
b100000000000001 !
$end
#5000
0]#
1Y#
b10000000000000 !
b10000000000000 )
0{"
1`#
1\#
1X#
1T#
1L#
1H#
1D#
1@#
1<#
18#
14#
10#
1,#
1(#
1~"
1z"
b1 "
b1 $
#10000
1U#
0Z#
0W#
1R#
1K#
0x"
0s"
1k"
b1000000000000 &
07"
0]#
0Y#
b1000000000000 !
b1000000000000 )
0{"
1v"
1r"
1n"
1j"
1f"
1b"
1^"
1Z"
1R"
1N"
1J"
1F"
1B"
1>"
1:"
16"
0`#
0\#
0X#
0T#
0L#
0H#
0D#
0@#
0<#
08#
04#
00#
0,#
0(#
0~"
0z"
b10 "
b10 $
#15000
0U#
b100000000000 !
b100000000000 )
1M#
1`#
1\#
1X#
1T#
1L#
1H#
1D#
1@#
1<#
18#
14#
10#
1,#
1(#
1~"
1z"
b11 "
b11 $
#20000
1I#
1F#
1C#
1c"
0]#
0{"
0p"
0i"
1`"
1Y"
04"
0Z#
0W#
0R#
0K#
0x"
0/"
1y
b10000000000 '
0M
0s"
0k"
b10000000000 &
07"
0U#
b10000000000 !
b10000000000 )
0M#
12"
1."
1&"
1""
1|
1x
1t
1p
1l
1h
1d
1`
1X
1T
1P
1L
0v"
0r"
0n"
0j"
0f"
0b"
0^"
0Z"
0R"
0N"
0J"
0F"
0B"
0>"
0:"
06"
0`#
0\#
0X#
0T#
0L#
0H#
0D#
0@#
0<#
08#
04#
00#
0,#
0(#
0~"
0z"
b100 "
b100 $
#25000
0I#
b1000000000 !
b1000000000 )
1E#
1`#
1\#
1X#
1T#
1L#
1H#
1D#
1@#
1<#
18#
14#
10#
1,#
1(#
1~"
1z"
b101 "
b101 $
#30000
1A#
0F#
0C#
1>#
1;#
0c"
b100000000 &
1["
0I#
b100000000 !
b100000000 )
0E#
1v"
1r"
1n"
1j"
1f"
1b"
1^"
1Z"
1R"
1N"
1J"
1F"
1B"
1>"
1:"
16"
0`#
0\#
0X#
0T#
0L#
0H#
0D#
0@#
0<#
08#
04#
00#
0,#
0(#
0~"
0z"
b110 "
b110 $
#35000
0A#
b10000000 !
b10000000 )
1=#
1`#
1\#
1X#
1T#
1L#
1H#
1D#
1@#
1<#
18#
14#
10#
1,#
1(#
1~"
1z"
b111 "
b111 $
#40000
19#
16#
13#
1O"
0]#
0{"
1L"
1E"
0Z#
0W#
0x"
1i
0s"
07"
0I#
0,"
0w
1f
1S
0J
0p"
0i"
0`"
0Y"
04"
0F#
0C#
0>#
0;#
0E
1Q#
b1000000 (
0-
0/"
0y
b1000000 '
0M
0c"
b1000000 &
0["
0A#
b1000000 !
b1000000 )
0=#
1H
1D
1@
1<
18
14
1l#
1h#
1d#
1P#
1$#
1V"
1*"
1\
10
1,
02"
0."
0&"
0""
0|
0x
0t
0p
0l
0h
0d
0`
0X
0T
0P
0L
0v"
0r"
0n"
0j"
0f"
0b"
0^"
0Z"
0R"
0N"
0J"
0F"
0B"
0>"
0:"
06"
0`#
0\#
0X#
0T#
0L#
0H#
0D#
0@#
0<#
08#
04#
00#
0,#
0(#
0~"
0z"
b1000 "
b1000 $
#45000
09#
b100000 !
b100000 )
15#
1`#
1\#
1X#
1T#
1L#
1H#
1D#
1@#
1<#
18#
14#
10#
1,#
1(#
1~"
1z"
b1001 "
b1001 $
#50000
11#
06#
03#
1.#
1+#
0O"
b10000 &
1G"
09#
b10000 !
b10000 )
05#
1v"
1r"
1n"
1j"
1f"
1b"
1^"
1Z"
1R"
1N"
1J"
1F"
1B"
1>"
1:"
16"
0`#
0\#
0X#
0T#
0L#
0H#
0D#
0@#
0<#
08#
04#
00#
0,#
0(#
0~"
0z"
b1010 "
b1010 $
#55000
01#
b1000 !
b1000 )
1-#
1`#
1\#
1X#
1T#
1L#
1H#
1D#
1@#
1<#
18#
14#
10#
1,#
1(#
1~"
1z"
b1011 "
b1011 $
#60000
1)#
1&#
1}"
1?"
09#
0L"
0E"
1<"
15"
06#
03#
0.#
0+#
0i
b100 '
1U
0O"
b100 &
0G"
01#
b100 !
b100 )
0-#
12"
1."
1&"
1""
1|
1x
1t
1p
1l
1h
1d
1`
1X
1T
1P
1L
0v"
0r"
0n"
0j"
0f"
0b"
0^"
0Z"
0R"
0N"
0J"
0F"
0B"
0>"
0:"
06"
0`#
0\#
0X#
0T#
0L#
0H#
0D#
0@#
0<#
08#
04#
00#
0,#
0(#
0~"
0z"
b1100 "
b1100 $
#65000
0)#
b10 !
b10 )
1!#
1`#
1\#
1X#
1T#
1L#
1H#
1D#
1@#
1<#
18#
14#
10#
1,#
1(#
1~"
1z"
b1101 "
b1101 $
#70000
1{"
0&#
0}"
1x"
0?"
b1 &
17"
0)#
b1 !
b1 )
0!#
1v"
1r"
1n"
1j"
1f"
1b"
1^"
1Z"
1R"
1N"
1J"
1F"
1B"
1>"
1:"
16"
0`#
0\#
0X#
0T#
0L#
0H#
0D#
0@#
0<#
08#
04#
00#
0,#
0(#
0~"
0z"
b1110 "
b1110 $
#75000
b0 !
b0 )
0{"
1`#
1\#
1X#
1T#
1L#
1H#
1D#
1@#
1<#
18#
14#
10#
1,#
1(#
1~"
1z"
b1111 "
b1111 $
